CHANGES.rst
LICENSE.GPL
LICENSE.txt
MANIFEST.in
README.rst
setup.py
leocornus/__init__.py
leocornus.recipe.wpmw.egg-info/PKG-INFO
leocornus.recipe.wpmw.egg-info/SOURCES.txt
leocornus.recipe.wpmw.egg-info/dependency_links.txt
leocornus.recipe.wpmw.egg-info/entry_points.txt
leocornus.recipe.wpmw.egg-info/namespace_packages.txt
leocornus.recipe.wpmw.egg-info/not-zip-safe
leocornus.recipe.wpmw.egg-info/requires.txt
leocornus.recipe.wpmw.egg-info/top_level.txt
leocornus/recipe/__init__.py
leocornus/recipe/wpmw/README.rst
leocornus/recipe/wpmw/__init__.py
leocornus/recipe/wpmw/test-wmflabs.rst
leocornus/recipe/wpmw/tests.py
leocornus/recipe/wpmw/testdata/repos/Cite.r37577.zip
leocornus/recipe/wpmw/testdata/repos/SemanticForms.1.9.1.zip
leocornus/recipe/wpmw/testdata/repos/SemanticMediaWiki.1.5.1.zip