Metadata-Version: 1.1
Name: leocornus.recipe.wpmw
Version: 1.3.3
Summary: zc.buildout recipe for managing WordPress plugins/themes and MediaWiki extensions
Home-page: http://github.com/leocornus/leocornus.recipe.wpmw
Author: Sean Chen
Author-email: sean.chen@leocorn.com
License: GPLv2
Keywords: development buildout recipe wordpress mediawiki
Platform: UNKNOWN
Classifier: Framework :: Buildout
Classifier: Intended Audience :: Developers
Classifier: License :: OSI Approved :: GNU General Public License (GPL)
Classifier: Topic :: Software Development :: Build Tools
Classifier: Topic :: Software Development :: Libraries :: Python Modules
